pynmf/__init__.py
pynmf/nmf.py
pynmf/postprocessing.py
pynmf/preprocessing.py
pynmf-0.1.0.dist-info/DESCRIPTION.rst
pynmf-0.1.0.dist-info/METADATA
pynmf-0.1.0.dist-info/RECORD
pynmf-0.1.0.dist-info/WHEEL
pynmf-0.1.0.dist-info/metadata.json
pynmf-0.1.0.dist-info/top_level.txt
