Metadata-Version: 2.0
Name: pynmf
Version: 0.1.0
Summary: non-negative matrix factorization algorithms for 2-photon processing
Home-page: https://github.com/cajal/pynmf
Author: Daniel Sourdry, Fabian Sinz, Edgar Y. Walker
Author-email: UNKNOWN
License: MIT
Keywords: neuroscientific data processing
Platform: UNKNOWN
Classifier: Intended Audience :: Science/Research
Classifier: Programming Language :: Python :: 3 :: Only
Requires-Dist: matplotlib
Requires-Dist: numpy
Requires-Dist: tifffile
